[{"ap_syndicated":null,"collect_date":"2022-08-07 19:00:06.527609","feeds":null,"guid":"https://www.nytimes.com/live/2022/08/07/us/climate-tax-deal-vote/sinemas-support-for-the-bill-hinged-in-part-on-a-single-tax-proposal","language":"en","media_id":1,"media_name":null,"media_url":null,"processed_stories_id":null,"publish_date":"2022-08-07 18:26:42","stories_id":2387891430,"story_tags":[{"stories_id":2387891430,"tag":"geonames_6252001","tag_set":"mc-geocoder@media.mit.edu","tag_sets_id":1011,"tags_id":8878461},{"stories_id":2387891430,"tag":"geonames_5128638","tag_set":"mc-geocoder@media.mit.edu","tag_sets_id":1011,"tags_id":8878463},{"stories_id":2387891430,"tag":"geonames_4826850","tag_set":"mc-geocoder@media.mit.edu","tag_sets_id":1011,"tags_id":8878580},{"stories_id":2387891430,"tag":"geonames_5879092","tag_set":"mc-geocoder@media.mit.edu","tag_sets_id":1011,"tags_id":8878759},{"stories_id":2387891430,"tag":"geonames_4140963","tag_set":"mc-geocoder@media.mit.edu","tag_sets_id":1011,"tags_id":8880349},{"stories_id":2387891430,"tag":"nyt_labeller_v1.0.0","tag_set":"nyt_labels_version","tag_sets_id":1964,"tags_id":9360669},{"stories_id":2387891430,"tag":"politics and government","tag_set":"nyt_labels","tag_sets_id":1963,"tags_id":9360836},{"stories_id":2387891430,"tag":"law and legislation","tag_set":"nyt_labels","tag_sets_id":1963,"tags_id":9360837},{"stories_id":2387891430,"tag":"finances","tag_set":"nyt_labels","tag_sets_id":1963,"tags_id":9360840},{"stories_id":2387891430,"tag":"medicine and health","tag_set":"nyt_labels","tag_sets_id":1963,"tags_id":9360852},{"stories_id":2387891430,"tag":"taxation","tag_set":"nyt_labels","tag_sets_id":1963,"tags_id":9360882},{"stories_id":2387891430,"tag":"editorials","tag_set":"nyt_labels","tag_sets_id":1963,"tags_id":9360894},{"stories_id":2387891430,"tag":"insurance","tag_set":"nyt_labels","tag_sets_id":1963,"tags_id":9360924},{"stories_id":2387891430,"tag":"health insurance and managed care","tag_set":"nyt_labels","tag_sets_id":1963,"tags_id":9360936},{"stories_id":2387891430,"tag":"drugs (pharmaceuticals)","tag_set":"nyt_labels","tag_sets_id":1963,"tags_id":9360941},{"stories_id":2387891430,"tag":"medicare","tag_set":"nyt_labels","tag_sets_id":1963,"tags_id":9361001},{"stories_id":2387891430,"tag":"Senate","tag_set":"cliff_organizations","tag_sets_id":2388,"tags_id":9362741},{"stories_id":2387891430,"tag":"Bernie Sanders","tag_set":"cliff_people","tag_sets_id":2389,"tags_id":9362750},{"stories_id":2387891430,"tag":"New York Times","tag_set":"cliff_organizations","tag_sets_id":2388,"tags_id":9362756},{"stories_id":2387891430,"tag":"Mitch McConnell","tag_set":"cliff_people","tag_sets_id":2389,"tags_id":9362936},{"stories_id":2387891430,"tag":"House","tag_set":"cliff_organizations","tag_sets_id":2388,"tags_id":9363164},{"stories_id":2387891430,"tag":"Kamala Harris","tag_set":"cliff_people","tag_sets_id":2389,"tags_id":9363331},{"stories_id":2387891430,"tag":"Lindsey Graham","tag_set":"cliff_people","tag_sets_id":2389,"tags_id":9363637},{"stories_id":2387891430,"tag":"Brian Schatz","tag_set":"cliff_people","tag_sets_id":2389,"tags_id":9364207},{"stories_id":2387891430,"tag":"Medicare","tag_set":"cliff_organizations","tag_sets_id":2388,"tags_id":9364657},{"stories_id":2387891430,"tag":"Chuck Schumer","tag_set":"cliff_people","tag_sets_id":2389,"tags_id":9364810},{"stories_id":2387891430,"tag":"Biden","tag_set":"cliff_people","tag_sets_id":2389,"tags_id":9365736},{"stories_id":2387891430,"tag":"I.R.S.","tag_set":"cliff_organizations","tag_sets_id":2388,"tags_id":9370174},{"stories_id":2387891430,"tag":"Kyrsten Sinema","tag_set":"cliff_people","tag_sets_id":2389,"tags_id":9381771},{"stories_id":2387891430,"tag":"Joe Manchin III","tag_set":"cliff_people","tag_sets_id":2389,"tags_id":9385885},{"stories_id":2387891430,"tag":"Lisa Friedman","tag_set":"cliff_people","tag_sets_id":2389,"tags_id":9421208},{"stories_id":2387891430,"tag":"Budget Committee","tag_set":"cliff_organizations","tag_sets_id":2388,"tags_id":9440487},{"stories_id":2387891430,"tag":"Jim Tankersley","tag_set":"cliff_people","tag_sets_id":2389,"tags_id":9456763},{"stories_id":2387891430,"tag":"T.J. Kirkpatrick","tag_set":"cliff_people","tag_sets_id":2389,"tags_id":9556938},{"stories_id":2387891430,"tag":"Tina Smith","tag_set":"cliff_people","tag_sets_id":2389,"tags_id":9589356},{"stories_id":2387891430,"tag":"Luke Broadwater","tag_set":"cliff_people","tag_sets_id":2389,"tags_id":10634678},{"stories_id":2387891430,"tag":"Stephanie Lai","tag_set":"cliff_people","tag_sets_id":2389,"tags_id":29970364},{"stories_id":2387891430,"tag":"readability-lxml-0.8.1","tag_set":"extractor_version","tag_sets_id":1354,"tags_id":228516910},{"stories_id":2387891430,"tag":"cliff_clavin_v2.6.1","tag_set":"geocoder_version","tag_sets_id":1937,"tags_id":228516911},{"stories_id":2387891430,"tag":"Haiyun Jiang/The","tag_set":"cliff_people","tag_sets_id":2389,"tags_id":256333288},{"stories_id":2387891430,"tag":"Vermont independent and Budget Committee","tag_set":"cliff_organizations","tag_sets_id":2388,"tags_id":259008643},{"stories_id":2387891430,"tag":"Alan Rappeport Sheryl Gay Stolberg","tag_set":"cliff_people","tag_sets_id":2389,"tags_id":259017256}],"title":"Sinema’s support for the bill hinged in part on a single tax proposal.","url":"https://www.nytimes.com/live/2022/08/07/us/climate-tax-deal-vote/sinemas-support-for-the-bill-hinged-in-part-on-a-single-tax-proposal","word_count":null}]