[{"ap_syndicated":null,"collect_date":"2019-02-17 19:35:32.185654","feeds":null,"guid":"http://feeds.reuters.com/~r/reuters/UKDomesticNews/~3/XqwLPM8kHTo/uk-britain-biomass-idUKBREA260EH20140307","language":"en","media_id":20438,"media_name":null,"media_url":null,"processed_stories_id":null,"publish_date":"2014-03-07 04:10:30","stories_id":1198766841,"story_tags":[{"stories_id":1198766841,"tag":"geonames_2635167","tag_set":"mc-geocoder@media.mit.edu","tag_sets_id":1011,"tags_id":8878466},{"stories_id":1198766841,"tag":"geonames_6269131","tag_set":"mc-geocoder@media.mit.edu","tag_sets_id":1011,"tags_id":8878467},{"stories_id":1198766841,"tag":"geonames_2643743","tag_set":"mc-geocoder@media.mit.edu","tag_sets_id":1011,"tags_id":8878473},{"stories_id":1198766841,"tag":"nyt_labeller_v1.0.0","tag_set":"nyt_labels_version","tag_sets_id":1964,"tags_id":9360669},{"stories_id":1198766841,"tag":"energy and power","tag_set":"nyt_labels","tag_sets_id":1963,"tags_id":9360997},{"stories_id":1198766841,"tag":"electric light and power","tag_set":"nyt_labels","tag_sets_id":1963,"tags_id":9361013},{"stories_id":1198766841,"tag":"light","tag_set":"nyt_labels","tag_sets_id":1963,"tags_id":9361014},{"stories_id":1198766841,"tag":"Reuters","tag_set":"cliff_organizations","tag_sets_id":2388,"tags_id":9362267},{"stories_id":1198766841,"tag":"Dale Hudson","tag_set":"cliff_people","tag_sets_id":2389,"tags_id":9381328},{"stories_id":1198766841,"tag":"RES","tag_set":"cliff_organizations","tag_sets_id":2388,"tags_id":9473518},{"stories_id":1198766841,"tag":"RWE","tag_set":"cliff_organizations","tag_sets_id":2388,"tags_id":9549513},{"stories_id":1198766841,"tag":"cliff_clavin_v2.4.1","tag_set":"geocoder_version","tag_sets_id":1937,"tags_id":9696677},{"stories_id":1198766841,"tag":"Nina Chestney","tag_set":"cliff_people","tag_sets_id":2389,"tags_id":11326051},{"stories_id":1198766841,"tag":"Gordon MacDougall","tag_set":"cliff_people","tag_sets_id":2389,"tags_id":68810385},{"stories_id":1198766841,"tag":"readability-lxml-0.7","tag_set":"extractor_version","tag_sets_id":1354,"tags_id":81092444}],"title":"UK biomass project halted, developer blames government policy","url":"http://feeds.reuters.com/~r/reuters/UKDomesticNews/~3/XqwLPM8kHTo/uk-britain-biomass-idUKBREA260EH20140307","word_count":null}]