[{"ap_syndicated":null,"collect_date":"2019-03-13 19:36:49.863277","feeds":null,"guid":"9121552507749","language":"en","media_id":1706,"media_name":null,"media_url":null,"processed_stories_id":null,"publish_date":"2019-03-13 19:24:21","stories_id":1222978602,"story_tags":[{"stories_id":1222978602,"tag":"geonames_3895114","tag_set":"mc-geocoder@media.mit.edu","tag_sets_id":1011,"tags_id":8878681},{"stories_id":1222978602,"tag":"geonames_3881974","tag_set":"mc-geocoder@media.mit.edu","tag_sets_id":1011,"tags_id":8893525},{"stories_id":1222978602,"tag":"nyt_labeller_v1.0.0","tag_set":"nyt_labels_version","tag_sets_id":1964,"tags_id":9360669},{"stories_id":1222978602,"tag":"global warming","tag_set":"nyt_labels","tag_sets_id":1963,"tags_id":9360886},{"stories_id":1222978602,"tag":"archaeology and anthropology","tag_set":"nyt_labels","tag_sets_id":1963,"tags_id":9360986},{"stories_id":1222978602,"tag":"space","tag_set":"nyt_labels","tag_sets_id":1963,"tags_id":9361032},{"stories_id":1222978602,"tag":"research","tag_set":"nyt_labels","tag_sets_id":1963,"tags_id":9361083},{"stories_id":1222978602,"tag":"UPI","tag_set":"cliff_organizations","tag_sets_id":2388,"tags_id":9375782},{"stories_id":1222978602,"tag":"Andrew Scott","tag_set":"cliff_people","tag_sets_id":2389,"tags_id":9452354},{"stories_id":1222978602,"tag":"Royal Holloway University of London","tag_set":"cliff_organizations","tag_sets_id":2388,"tags_id":9621866},{"stories_id":1222978602,"tag":"cliff_clavin_v2.4.1","tag_set":"geocoder_version","tag_sets_id":1937,"tags_id":9696677},{"stories_id":1222978602,"tag":"University of California, Santa Barbara","tag_set":"cliff_organizations","tag_sets_id":2388,"tags_id":9699606},{"stories_id":1222978602,"tag":"journal","tag_set":"cliff_organizations","tag_sets_id":2388,"tags_id":9713576},{"stories_id":1222978602,"tag":"James Kennett","tag_set":"cliff_people","tag_sets_id":2389,"tags_id":23714842},{"stories_id":1222978602,"tag":"sabertooth cats","tag_set":"cliff_organizations","tag_sets_id":2388,"tags_id":48741054},{"stories_id":1222978602,"tag":"readability-lxml-0.7","tag_set":"extractor_version","tag_sets_id":1354,"tags_id":81092444}],"title":"Ancient comet impact triggered fires, climate change, megafauna extinctions","url":"https://www.upi.com/Science_News/2019/03/13/Ancient-comet-impact-triggered-fires-climate-change/9121552507749/","word_count":null}]