[{"ap_syndicated":null,"collect_date":"2019-05-22 14:48:00.729586","feeds":null,"guid":"/one-billion-old-fungi-found-earths-oldest-174444170.html","language":"en","media_id":19883,"media_name":null,"media_url":null,"processed_stories_id":null,"publish_date":"2019-05-22 13:44:44","stories_id":1290428618,"story_tags":[{"stories_id":1290428618,"tag":"geonames_6251999","tag_set":"mc-geocoder@media.mit.edu","tag_sets_id":1011,"tags_id":8878548},{"stories_id":1290428618,"tag":"geonames_2802361","tag_set":"mc-geocoder@media.mit.edu","tag_sets_id":1011,"tags_id":8879013},{"stories_id":1290428618,"tag":"nyt_labeller_v1.0.0","tag_set":"nyt_labels_version","tag_sets_id":1964,"tags_id":9360669},{"stories_id":1290428618,"tag":"archaeology and anthropology","tag_set":"nyt_labels","tag_sets_id":1963,"tags_id":9360986},{"stories_id":1290428618,"tag":"space","tag_set":"nyt_labels","tag_sets_id":1963,"tags_id":9361032},{"stories_id":1290428618,"tag":"research","tag_set":"nyt_labels","tag_sets_id":1963,"tags_id":9361083},{"stories_id":1290428618,"tag":"biology and biochemistry","tag_set":"nyt_labels","tag_sets_id":1963,"tags_id":9361179},{"stories_id":1290428618,"tag":"University of Liege","tag_set":"cliff_organizations","tag_sets_id":2388,"tags_id":9674175},{"stories_id":1290428618,"tag":"cliff_clavin_v2.4.1","tag_set":"geocoder_version","tag_sets_id":1937,"tags_id":9696677},{"stories_id":1290428618,"tag":"AFP","tag_set":"cliff_organizations","tag_sets_id":2388,"tags_id":9696691},{"stories_id":1290428618,"tag":"readability-lxml-0.7","tag_set":"extractor_version","tag_sets_id":1354,"tags_id":81092444},{"stories_id":1290428618,"tag":"Corentin Loron","tag_set":"cliff_people","tag_sets_id":2389,"tags_id":162624300}],"title":"One billion year old fungi found is Earth&#39;s oldest","url":"https://sg.news.yahoo.com/one-billion-old-fungi-found-earths-oldest-174444170.html","word_count":null}]