[{"ap_syndicated":null,"collect_date":"2019-11-16 01:43:21.129091","feeds":null,"guid":"\n\thttps://www.dailymail.co.uk/news/article-7691843/Heather-Mills-says-algae-pond-slime-future-food.html?ns_mchannel=rss&ito=1490&ns_campaign=1490\n      ","language":"en","media_id":19142,"media_name":null,"media_url":null,"processed_stories_id":null,"publish_date":"2019-11-15 20:15:56","stories_id":1446524415,"story_tags":[{"stories_id":1446524415,"tag":"geonames_2635167","tag_set":"mc-geocoder@media.mit.edu","tag_sets_id":1011,"tags_id":8878466},{"stories_id":1446524415,"tag":"geonames_6269131","tag_set":"mc-geocoder@media.mit.edu","tag_sets_id":1011,"tags_id":8878467},{"stories_id":1446524415,"tag":"nyt_labeller_v1.0.0","tag_set":"nyt_labels_version","tag_sets_id":1964,"tags_id":9360669},{"stories_id":1446524415,"tag":"food","tag_set":"nyt_labels","tag_sets_id":1963,"tags_id":9361010},{"stories_id":1446524415,"tag":"Paul McCartney","tag_set":"cliff_people","tag_sets_id":2389,"tags_id":9372825},{"stories_id":1446524415,"tag":"Heather Mills","tag_set":"cliff_people","tag_sets_id":2389,"tags_id":9468604},{"stories_id":1446524415,"tag":"readability-lxml-0.7","tag_set":"extractor_version","tag_sets_id":1354,"tags_id":81092444},{"stories_id":1446524415,"tag":"cliff_clavin_v2.6.0","tag_set":"geocoder_version","tag_sets_id":1937,"tags_id":189462640},{"stories_id":1446524415,"tag":"VBites vegan food company","tag_set":"cliff_organizations","tag_sets_id":2388,"tags_id":190085981}],"title":"\n\tHeather Mills says algae (pond slime) could be the future of food\n      ","url":"https://www.dailymail.co.uk/news/article-7691843/Heather-Mills-says-algae-pond-slime-future-food.html?ns_mchannel=rss&ito=1490&ns_campaign=1490","word_count":null}]