[{"ap_syndicated":null,"collect_date":"2013-10-26 06:18:50","feeds":null,"guid":"http://www.dnaindia.com/money/interview-punjab-offers-cheapest-power-easiest-policies-to-industries-1908982","language":"en","media_id":65929,"media_name":null,"media_url":null,"processed_stories_id":null,"publish_date":"2013-10-26 04:36:00","stories_id":168282146,"story_tags":[{"stories_id":168282146,"tag":"geonames_1269750","tag_set":"mc-geocoder@media.mit.edu","tag_sets_id":1011,"tags_id":8878677},{"stories_id":168282146,"tag":"geonames_1259223","tag_set":"mc-geocoder@media.mit.edu","tag_sets_id":1011,"tags_id":8881654},{"stories_id":168282146,"tag":"readability-lxml-0.6.2","tag_set":"extractor_version","tag_sets_id":1354,"tags_id":9325058},{"stories_id":168282146,"tag":"nyt_labeller_v1.0.0","tag_set":"nyt_labels_version","tag_sets_id":1964,"tags_id":9360669},{"stories_id":168282146,"tag":"Mahindra & Mahindra","tag_set":"cliff_organizations","tag_sets_id":2388,"tags_id":9432322},{"stories_id":168282146,"tag":"Sukhbir Singh Badal","tag_set":"cliff_people","tag_sets_id":2389,"tags_id":9432592},{"stories_id":168282146,"tag":"APCO","tag_set":"cliff_organizations","tag_sets_id":2388,"tags_id":9441046},{"stories_id":168282146,"tag":"kitty","tag_set":"cliff_people","tag_sets_id":2389,"tags_id":9460915},{"stories_id":168282146,"tag":"cliff_clavin_v2.4.1","tag_set":"geocoder_version","tag_sets_id":1937,"tags_id":9696677},{"stories_id":168282146,"tag":"Prakash Singh Badal","tag_set":"cliff_people","tag_sets_id":2389,"tags_id":10994842},{"stories_id":168282146,"tag":"Sudhir Chaudhary","tag_set":"cliff_people","tag_sets_id":2389,"tags_id":13670019},{"stories_id":168282146,"tag":"Kanchan Srivastava","tag_set":"cliff_people","tag_sets_id":2389,"tags_id":38471035}],"title":"Punjab offers cheapest power, easiest policies to industries","url":"http://www.dnaindia.com/money/interview-punjab-offers-cheapest-power-easiest-policies-to-industries-1908982","word_count":null}]