[{"ap_syndicated":null,"collect_date":"2020-11-04 12:46:45.532077","feeds":null,"guid":"https://theconversation.com/profiles/marina-ezcurra-1107358","language":"en","media_id":54346,"media_name":null,"media_url":null,"processed_stories_id":null,"publish_date":"2020-06-08 16:32:12","stories_id":1759806363,"story_tags":[{"stories_id":1759806363,"tag":"geonames_2635167","tag_set":"mc-geocoder@media.mit.edu","tag_sets_id":1011,"tags_id":8878466},{"stories_id":1759806363,"tag":"geonames_6269131","tag_set":"mc-geocoder@media.mit.edu","tag_sets_id":1011,"tags_id":8878467},{"stories_id":1759806363,"tag":"geonames_2661886","tag_set":"mc-geocoder@media.mit.edu","tag_sets_id":1011,"tags_id":8878620},{"stories_id":1759806363,"tag":"geonames_2673722","tag_set":"mc-geocoder@media.mit.edu","tag_sets_id":1011,"tags_id":8878870},{"stories_id":1759806363,"tag":"geonames_2653941","tag_set":"mc-geocoder@media.mit.edu","tag_sets_id":1011,"tags_id":8878989},{"stories_id":1759806363,"tag":"nyt_labeller_v1.0.0","tag_set":"nyt_labels_version","tag_sets_id":1964,"tags_id":9360669},{"stories_id":1759806363,"tag":"medicine and health","tag_set":"nyt_labels","tag_sets_id":1963,"tags_id":9360852},{"stories_id":1759806363,"tag":"research","tag_set":"nyt_labels","tag_sets_id":1963,"tags_id":9361083},{"stories_id":1759806363,"tag":"genetics and heredity","tag_set":"nyt_labels","tag_sets_id":1963,"tags_id":9361140},{"stories_id":1759806363,"tag":"University College London","tag_set":"cliff_organizations","tag_sets_id":2388,"tags_id":9365106},{"stories_id":1759806363,"tag":"David","tag_set":"cliff_people","tag_sets_id":2389,"tags_id":9367183},{"stories_id":1759806363,"tag":"Karolinska Institute","tag_set":"cliff_organizations","tag_sets_id":2388,"tags_id":9391901},{"stories_id":1759806363,"tag":"Royal Society","tag_set":"cliff_organizations","tag_sets_id":2388,"tags_id":9398249},{"stories_id":1759806363,"tag":"Wellcome Trust","tag_set":"cliff_organizations","tag_sets_id":2388,"tags_id":9398253},{"stories_id":1759806363,"tag":"C. elegans","tag_set":"cliff_people","tag_sets_id":2389,"tags_id":9621730},{"stories_id":1759806363,"tag":"Marina Ezcurra","tag_set":"cliff_people","tag_sets_id":2389,"tags_id":29650430},{"stories_id":1759806363,"tag":"Bill Schafer","tag_set":"cliff_people","tag_sets_id":2389,"tags_id":34796109},{"stories_id":1759806363,"tag":"guess_by_tag_meta","tag_set":"date_guess_method","tag_sets_id":508,"tags_id":50741386},{"stories_id":1759806363,"tag":"readability-lxml-0.7","tag_set":"extractor_version","tag_sets_id":1354,"tags_id":81092444},{"stories_id":1759806363,"tag":"cliff_clavin_v2.6.0","tag_set":"geocoder_version","tag_sets_id":1937,"tags_id":189462640},{"stories_id":1759806363,"tag":"British Society of Research","tag_set":"cliff_organizations","tag_sets_id":2388,"tags_id":219568162}],"title":"Marina Ezcurra","url":"https://theconversation.com/profiles/marina-ezcurra-1107358","word_count":null}]