[{"ap_syndicated":null,"collect_date":"2014-12-31 19:34:07","feeds":null,"guid":"http://www.huffingtonpost.com/2014/12/31/best-architecture-2014_n_6397524.html","language":"en","media_id":27502,"media_name":null,"media_url":null,"processed_stories_id":null,"publish_date":"2014-12-31 17:51:13","stories_id":305973410,"story_tags":[{"stories_id":305973410,"tag":"geonames_6252001","tag_set":"mc-geocoder@media.mit.edu","tag_sets_id":1011,"tags_id":8878461},{"stories_id":305973410,"tag":"geonames_1814991","tag_set":"mc-geocoder@media.mit.edu","tag_sets_id":1011,"tags_id":8878478},{"stories_id":305973410,"tag":"geonames_5165418","tag_set":"mc-geocoder@media.mit.edu","tag_sets_id":1011,"tags_id":8878703},{"stories_id":305973410,"tag":"readability-lxml-0.3.0.5","tag_set":"extractor_version","tag_sets_id":1354,"tags_id":8929188},{"stories_id":305973410,"tag":"nyt_labeller_v1.0.0","tag_set":"nyt_labels_version","tag_sets_id":1964,"tags_id":9360669},{"stories_id":305973410,"tag":"travel and vacations","tag_set":"nyt_labels","tag_sets_id":1963,"tags_id":9361022},{"stories_id":305973410,"tag":"housing","tag_set":"nyt_labels","tag_sets_id":1963,"tags_id":9361048},{"stories_id":305973410,"tag":"architecture","tag_set":"nyt_labels","tag_sets_id":1963,"tags_id":9361299},{"stories_id":305973410,"tag":"David Benjamin","tag_set":"cliff_people","tag_sets_id":2389,"tags_id":9420347},{"stories_id":305973410,"tag":"LEGO House","tag_set":"cliff_organizations","tag_sets_id":2388,"tags_id":9540530},{"stories_id":305973410,"tag":"Fernando Guerra","tag_set":"cliff_people","tag_sets_id":2389,"tags_id":9614040},{"stories_id":305973410,"tag":"cliff_clavin_v2.4.1","tag_set":"geocoder_version","tag_sets_id":1937,"tags_id":9696677},{"stories_id":305973410,"tag":"Hu","tag_set":"cliff_people","tag_sets_id":2389,"tags_id":10007364},{"stories_id":305973410,"tag":"Hotchkiss School","tag_set":"cliff_organizations","tag_sets_id":2388,"tags_id":10120948},{"stories_id":305973410,"tag":"Neri","tag_set":"cliff_people","tag_sets_id":2389,"tags_id":10354760},{"stories_id":305973410,"tag":"Artnet","tag_set":"cliff_people","tag_sets_id":2389,"tags_id":10408501},{"stories_id":305973410,"tag":"LEGO group","tag_set":"cliff_organizations","tag_sets_id":2388,"tags_id":28542442},{"stories_id":305973410,"tag":"Craig Steely","tag_set":"cliff_people","tag_sets_id":2389,"tags_id":28885715},{"stories_id":305973410,"tag":"Gustavo Penna","tag_set":"cliff_people","tag_sets_id":2389,"tags_id":29461681},{"stories_id":305973410,"tag":"architec","tag_set":"cliff_organizations","tag_sets_id":2388,"tags_id":31235961},{"stories_id":305973410,"tag":"Centerbrook","tag_set":"cliff_organizations","tag_sets_id":2388,"tags_id":31278969},{"stories_id":305973410,"tag":"Farshad Mehdizadeh","tag_set":"cliff_people","tag_sets_id":2389,"tags_id":31547608},{"stories_id":305973410,"tag":"Sergio Guerra","tag_set":"cliff_people","tag_sets_id":2389,"tags_id":32211256},{"stories_id":305973410,"tag":"Fearon Hay","tag_set":"cliff_people","tag_sets_id":2389,"tags_id":35846603},{"stories_id":305973410,"tag":"Dune House","tag_set":"cliff_organizations","tag_sets_id":2388,"tags_id":38994172},{"stories_id":305973410,"tag":"Aires Mateus","tag_set":"cliff_people","tag_sets_id":2389,"tags_id":40036599},{"stories_id":305973410,"tag":"Adam Mõrk","tag_set":"cliff_people","tag_sets_id":2389,"tags_id":74491090},{"stories_id":305973410,"tag":"Urko Sanchez","tag_set":"cliff_people","tag_sets_id":2389,"tags_id":74491094},{"stories_id":305973410,"tag":"Alberto Heras","tag_set":"cliff_people","tag_sets_id":2389,"tags_id":74491095},{"stories_id":305973410,"tag":"David Sundberg/Esto","tag_set":"cliff_people","tag_sets_id":2389,"tags_id":74491096},{"stories_id":305973410,"tag":"Tiago Rebelo de Andrade","tag_set":"cliff_people","tag_sets_id":2389,"tags_id":74491097},{"stories_id":305973410,"tag":"Ricardo Oliveira Alves","tag_set":"cliff_people","tag_sets_id":2389,"tags_id":74491098},{"stories_id":305973410,"tag":"Cachoua Torres Camilletti","tag_set":"cliff_people","tag_sets_id":2389,"tags_id":74491100},{"stories_id":305973410,"tag":"Corbasson","tag_set":"cliff_people","tag_sets_id":2389,"tags_id":74491101},{"stories_id":305973410,"tag":"Farshad Mehdizadeh Architects","tag_set":"cliff_organizations","tag_sets_id":2388,"tags_id":74491106},{"stories_id":305973410,"tag":"Arquiteto & Associates","tag_set":"cliff_organizations","tag_sets_id":2388,"tags_id":74491107},{"stories_id":305973410,"tag":"Red Pepper House","tag_set":"cliff_organizations","tag_sets_id":2388,"tags_id":74491108},{"stories_id":305973410,"tag":"Hotchkiss Biomass Power Plant","tag_set":"cliff_organizations","tag_sets_id":2388,"tags_id":74491109},{"stories_id":305973410,"tag":"Hebie Academy of Fine Arts","tag_set":"cliff_organizations","tag_sets_id":2388,"tags_id":74491110}],"title":"20 Of The Most Ingenious Works Of Architecture In 2014","url":"http://www.huffingtonpost.com/2014/12/31/best-architecture-2014_n_6397524.html?utm_hp_ref=arts&ir=Arts","word_count":null}]