[{"ap_syndicated":null,"collect_date":"2016-06-27 01:49:49.515891","feeds":null,"guid":"http://www.dailymirror.lk/111544/Say-no-to-coal-for-a-greener-safer-environment","language":"en","media_id":61084,"media_name":null,"media_url":null,"processed_stories_id":null,"publish_date":"2016-06-26 19:22:12","stories_id":482408236,"story_tags":[{"stories_id":482408236,"tag":"geonames_1227603","tag_set":"mc-geocoder@media.mit.edu","tag_sets_id":1011,"tags_id":8878890},{"stories_id":482408236,"tag":"geonames_1253626","tag_set":"mc-geocoder@media.mit.edu","tag_sets_id":1011,"tags_id":8880766},{"stories_id":482408236,"tag":"readability-lxml-0.3.0.5","tag_set":"extractor_version","tag_sets_id":1354,"tags_id":8929188},{"stories_id":482408236,"tag":"nyt_labeller_v1.0.0","tag_set":"nyt_labels_version","tag_sets_id":1964,"tags_id":9360669},{"stories_id":482408236,"tag":"global warming","tag_set":"nyt_labels","tag_sets_id":1963,"tags_id":9360886},{"stories_id":482408236,"tag":"energy and power","tag_set":"nyt_labels","tag_sets_id":1963,"tags_id":9360997},{"stories_id":482408236,"tag":"electric light and power","tag_set":"nyt_labels","tag_sets_id":1963,"tags_id":9361013},{"stories_id":482408236,"tag":"light","tag_set":"nyt_labels","tag_sets_id":1963,"tags_id":9361014},{"stories_id":482408236,"tag":"United Nations","tag_set":"cliff_organizations","tag_sets_id":2388,"tags_id":9362785},{"stories_id":482408236,"tag":"General Assembly","tag_set":"cliff_organizations","tag_sets_id":2388,"tags_id":9362801},{"stories_id":482408236,"tag":"IMF","tag_set":"cliff_organizations","tag_sets_id":2388,"tags_id":9367709},{"stories_id":482408236,"tag":"Mitsubishi","tag_set":"cliff_organizations","tag_sets_id":2388,"tags_id":9373295},{"stories_id":482408236,"tag":"Fukushima","tag_set":"cliff_people","tag_sets_id":2389,"tags_id":9374455},{"stories_id":482408236,"tag":"Susil Premajayantha","tag_set":"cliff_people","tag_sets_id":2389,"tags_id":9380030},{"stories_id":482408236,"tag":"EIA","tag_set":"cliff_organizations","tag_sets_id":2388,"tags_id":9411071},{"stories_id":482408236,"tag":"CPC","tag_set":"cliff_organizations","tag_sets_id":2388,"tags_id":9453147},{"stories_id":482408236,"tag":"cliff_clavin_v2.4.1","tag_set":"geocoder_version","tag_sets_id":1937,"tags_id":9696677},{"stories_id":482408236,"tag":"CEB","tag_set":"cliff_organizations","tag_sets_id":2388,"tags_id":9773602},{"stories_id":482408236,"tag":"Petroleum Corporation","tag_set":"cliff_organizations","tag_sets_id":2388,"tags_id":9777503},{"stories_id":482408236,"tag":"Ruhuna","tag_set":"cliff_people","tag_sets_id":2389,"tags_id":10366038},{"stories_id":482408236,"tag":"Mitsubishi Company","tag_set":"cliff_organizations","tag_sets_id":2388,"tags_id":32189704},{"stories_id":482408236,"tag":"Ministry of Power and Energy","tag_set":"cliff_organizations","tag_sets_id":2388,"tags_id":32409052},{"stories_id":482408236,"tag":"Dendro","tag_set":"cliff_people","tag_sets_id":2389,"tags_id":35654522},{"stories_id":482408236,"tag":"Noraichcholai coal power plant","tag_set":"cliff_organizations","tag_sets_id":2388,"tags_id":104059493},{"stories_id":482408236,"tag":"Sampur coal power plant","tag_set":"cliff_organizations","tag_sets_id":2388,"tags_id":109046236}],"title":"Say no to coal for a greener, safer environment","url":"http://www.dailymirror.lk/111544/Say-no-to-coal-for-a-greener-safer-environment","word_count":null}]