[{"ap_syndicated":null,"collect_date":"2017-08-17 21:47:43","feeds":null,"guid":"https://www.scientificamerican.com/article/native-plants-on-marginal-lands-to-reduce-food-versus-fuel-from-biofuels/","language":"en","media_id":38941,"media_name":null,"media_url":null,"processed_stories_id":null,"publish_date":"2017-06-07 08:02:57","stories_id":676128338,"story_tags":[{"stories_id":676128338,"tag":"spidered","tag_set":"spidered","tag_sets_id":183,"tags_id":8875452},{"stories_id":676128338,"tag":"undateable","tag_set":"date_invalid","tag_sets_id":714,"tags_id":8877812},{"stories_id":676128338,"tag":"geonames_6252001","tag_set":"mc-geocoder@media.mit.edu","tag_sets_id":1011,"tags_id":8878461},{"stories_id":676128338,"tag":"readability-lxml-0.6.2","tag_set":"extractor_version","tag_sets_id":1354,"tags_id":9325058},{"stories_id":676128338,"tag":"nyt_labeller_v1.0.0","tag_set":"nyt_labels_version","tag_sets_id":1964,"tags_id":9360669},{"stories_id":676128338,"tag":"oil (petroleum) and gasoline","tag_set":"nyt_labels","tag_sets_id":1963,"tags_id":9360884},{"stories_id":676128338,"tag":"environment","tag_set":"nyt_labels","tag_sets_id":1963,"tags_id":9360887},{"stories_id":676128338,"tag":"international trade and world market","tag_set":"nyt_labels","tag_sets_id":1963,"tags_id":9360983},{"stories_id":676128338,"tag":"prices (fares, fees and rates)","tag_set":"nyt_labels","tag_sets_id":1963,"tags_id":9360996},{"stories_id":676128338,"tag":"energy and power","tag_set":"nyt_labels","tag_sets_id":1963,"tags_id":9360997},{"stories_id":676128338,"tag":"food","tag_set":"nyt_labels","tag_sets_id":1963,"tags_id":9361010},{"stories_id":676128338,"tag":"agriculture","tag_set":"nyt_labels","tag_sets_id":1963,"tags_id":9361156},{"stories_id":676128338,"tag":"grain","tag_set":"nyt_labels","tag_sets_id":1963,"tags_id":9361168},{"stories_id":676128338,"tag":"farmers","tag_set":"nyt_labels","tag_sets_id":1963,"tags_id":9361177},{"stories_id":676128338,"tag":"flowers and plants","tag_set":"nyt_labels","tag_sets_id":1963,"tags_id":9361260},{"stories_id":676128338,"tag":"U.N.","tag_set":"cliff_organizations","tag_sets_id":2388,"tags_id":9363619},{"stories_id":676128338,"tag":"Congressional Budget Office","tag_set":"cliff_organizations","tag_sets_id":2388,"tags_id":9364202},{"stories_id":676128338,"tag":"Michigan State University","tag_set":"cliff_organizations","tag_sets_id":2388,"tags_id":9375856},{"stories_id":676128338,"tag":"Princeton University","tag_set":"cliff_organizations","tag_sets_id":2388,"tags_id":9384802},{"stories_id":676128338,"tag":"U.S. Department of Energy","tag_set":"cliff_organizations","tag_sets_id":2388,"tags_id":9414255},{"stories_id":676128338,"tag":"Timothy Searchinger","tag_set":"cliff_people","tag_sets_id":2389,"tags_id":9486277},{"stories_id":676128338,"tag":"Karlsruhe Institute of Technology","tag_set":"cliff_organizations","tag_sets_id":2388,"tags_id":9517781},{"stories_id":676128338,"tag":"cliff_clavin_v2.4.1","tag_set":"geocoder_version","tag_sets_id":1937,"tags_id":9696677},{"stories_id":676128338,"tag":"Ralf Kiese","tag_set":"cliff_people","tag_sets_id":2389,"tags_id":31689970},{"stories_id":676128338,"tag":"Klaus Butterbach-Bahl","tag_set":"cliff_people","tag_sets_id":2389,"tags_id":43622552},{"stories_id":676128338,"tag":"Ilya Gelfand","tag_set":"cliff_people","tag_sets_id":2389,"tags_id":44440828}],"title":"Food versus Fuel: Native Plants Make Better Ethanol","url":"https://www.scientificamerican.com/article/native-plants-on-marginal-lands-to-reduce-food-versus-fuel-from-biofuels/","word_count":null}]