[{"ap_syndicated":null,"collect_date":"2017-08-31 01:12:30.281186","feeds":null,"guid":"http://www.canadianbusiness.com/?p=1059645","language":"en","media_id":20662,"media_name":null,"media_url":null,"processed_stories_id":null,"publish_date":"2017-08-29 16:29:19","stories_id":682641004,"story_tags":[{"stories_id":682641004,"tag":"geonames_6251999","tag_set":"mc-geocoder@media.mit.edu","tag_sets_id":1011,"tags_id":8878548},{"stories_id":682641004,"tag":"geonames_6091530","tag_set":"mc-geocoder@media.mit.edu","tag_sets_id":1011,"tags_id":8879860},{"stories_id":682641004,"tag":"readability-lxml-0.6.2","tag_set":"extractor_version","tag_sets_id":1354,"tags_id":9325058},{"stories_id":682641004,"tag":"cliff_clavin_v2.3.0","tag_set":"geocoder_version","tag_sets_id":1937,"tags_id":9353691},{"stories_id":682641004,"tag":"nyt_labeller_v1.0.0","tag_set":"nyt_labels_version","tag_sets_id":1964,"tags_id":9360669}],"title":"Nova Scotia review of forestry practices needs to tackle clear cutting:group","url":"http://www.canadianbusiness.com/business-news/nova-scotia-review-of-forestry-practices-needs-to-tackle-clear-cuttinggroup/","word_count":null}]