[{"ap_syndicated":null,"collect_date":"2018-06-06 03:15:56.235175","feeds":null,"guid":"255158","language":"en","media_id":144205,"media_name":null,"media_url":null,"processed_stories_id":null,"publish_date":"2018-06-06 04:05:13","stories_id":894288579,"story_tags":[{"stories_id":894288579,"tag":"geonames_2328926","tag_set":"mc-geocoder@media.mit.edu","tag_sets_id":1011,"tags_id":8878919},{"stories_id":894288579,"tag":"geonames_2324828","tag_set":"mc-geocoder@media.mit.edu","tag_sets_id":1011,"tags_id":8925227},{"stories_id":894288579,"tag":"readability-lxml-0.6.2","tag_set":"extractor_version","tag_sets_id":1354,"tags_id":9325058},{"stories_id":894288579,"tag":"nyt_labeller_v1.0.0","tag_set":"nyt_labels_version","tag_sets_id":1964,"tags_id":9360669},{"stories_id":894288579,"tag":"education and schools","tag_set":"nyt_labels","tag_sets_id":1963,"tags_id":9360833},{"stories_id":894288579,"tag":"environment","tag_set":"nyt_labels","tag_sets_id":1963,"tags_id":9360887},{"stories_id":894288579,"tag":"energy and power","tag_set":"nyt_labels","tag_sets_id":1963,"tags_id":9360997},{"stories_id":894288579,"tag":"air pollution","tag_set":"nyt_labels","tag_sets_id":1963,"tags_id":9361007},{"stories_id":894288579,"tag":"electric light and power","tag_set":"nyt_labels","tag_sets_id":1963,"tags_id":9361013},{"stories_id":894288579,"tag":"light","tag_set":"nyt_labels","tag_sets_id":1963,"tags_id":9361014},{"stories_id":894288579,"tag":"water","tag_set":"nyt_labels","tag_sets_id":1963,"tags_id":9361151},{"stories_id":894288579,"tag":"ECOWAS","tag_set":"cliff_organizations","tag_sets_id":2388,"tags_id":9362986},{"stories_id":894288579,"tag":"European Union","tag_set":"cliff_organizations","tag_sets_id":2388,"tags_id":9362999},{"stories_id":894288579,"tag":"Babatunde Fashola","tag_set":"cliff_people","tag_sets_id":2389,"tags_id":9368811},{"stories_id":894288579,"tag":"PPP","tag_set":"cliff_organizations","tag_sets_id":2388,"tags_id":9369555},{"stories_id":894288579,"tag":"Jos","tag_set":"cliff_people","tag_sets_id":2389,"tags_id":9373209},{"stories_id":894288579,"tag":"LGA","tag_set":"cliff_organizations","tag_sets_id":2388,"tags_id":9391089},{"stories_id":894288579,"tag":"GSS","tag_set":"cliff_organizations","tag_sets_id":2388,"tags_id":9460263},{"stories_id":894288579,"tag":"Simon Lalong","tag_set":"cliff_people","tag_sets_id":2389,"tags_id":9504926},{"stories_id":894288579,"tag":"cliff_clavin_v2.4.1","tag_set":"geocoder_version","tag_sets_id":1937,"tags_id":9696677},{"stories_id":894288579,"tag":"Kuru","tag_set":"cliff_people","tag_sets_id":2389,"tags_id":10274076},{"stories_id":894288579,"tag":"Regine Hess","tag_set":"cliff_people","tag_sets_id":2389,"tags_id":33346941},{"stories_id":894288579,"tag":"Faruk Yabo","tag_set":"cliff_people","tag_sets_id":2389,"tags_id":35572962},{"stories_id":894288579,"tag":"Kurt Cornelis","tag_set":"cliff_people","tag_sets_id":2389,"tags_id":36021890}],"title":"Environment","url":"https://www.dailytrust.com.ng/when-plateau-adopted-clean-energy-to-fight-pollution-provide-power-255158.html","word_count":null}]