[{"ap_syndicated":null,"collect_date":"2020-02-09 08:33:13.524662","feeds":null,"guid":"https://www.newsweek.com/trump-tying-business-diplomacy-golf-course-1351005?utm_source=Twitter&utm_medium=Social&utm_campaign=NewsweekTwitter","language":"en","media_id":2,"media_name":null,"media_url":null,"processed_stories_id":null,"publish_date":"2019-03-04 16:39:48","stories_id":1516238526,"story_tags":[{"stories_id":1516238526,"tag":"guess_by_tag_meta","tag_set":"date_guess_method","tag_sets_id":508,"tags_id":50741386}],"title":"Trump 'Explicitly Tying His Personal Business Interests' to U.S. Diplomacy, Experts Warn After Golf Course Tweet","url":"https://www.newsweek.com/trump-tying-business-diplomacy-golf-course-1351005?utm_source=Twitter&utm_medium=Social&utm_campaign=NewsweekTwitter","word_count":null}]