[{"ap_syndicated":null,"collect_date":"2016-11-07 14:20:49.979802","feeds":null,"guid":"http://www.newsweek.com/climate-change-and-policy-statewide-races-watch-517971","language":"en","media_id":56510,"media_name":null,"media_url":null,"processed_stories_id":null,"publish_date":"2016-11-07 13:49:58","stories_id":538278012,"story_tags":[{"stories_id":538278012,"tag":"geonames_6252001","tag_set":"mc-geocoder@media.mit.edu","tag_sets_id":1011,"tags_id":8878461},{"stories_id":538278012,"tag":"geonames_4398678","tag_set":"mc-geocoder@media.mit.edu","tag_sets_id":1011,"tags_id":8878483},{"stories_id":538278012,"tag":"geonames_4998574","tag_set":"mc-geocoder@media.mit.edu","tag_sets_id":1011,"tags_id":8879095},{"stories_id":538278012,"tag":"nyt_labeller_v1.0.0","tag_set":"nyt_labels_version","tag_sets_id":1964,"tags_id":9360669},{"stories_id":538278012,"tag":"politics and government","tag_set":"nyt_labels","tag_sets_id":1963,"tags_id":9360836},{"stories_id":538278012,"tag":"elections","tag_set":"nyt_labels","tag_sets_id":1963,"tags_id":9360851},{"stories_id":538278012,"tag":"global warming","tag_set":"nyt_labels","tag_sets_id":1963,"tags_id":9360886},{"stories_id":538278012,"tag":"environment","tag_set":"nyt_labels","tag_sets_id":1963,"tags_id":9360887},{"stories_id":538278012,"tag":"weather","tag_set":"nyt_labels","tag_sets_id":1963,"tags_id":9360902},{"stories_id":538278012,"tag":"energy and power","tag_set":"nyt_labels","tag_sets_id":1963,"tags_id":9360997},{"stories_id":538278012,"tag":"air pollution","tag_set":"nyt_labels","tag_sets_id":1963,"tags_id":9361007},{"stories_id":538278012,"tag":"Donald Trump","tag_set":"cliff_people","tag_sets_id":2389,"tags_id":9362284},{"stories_id":538278012,"tag":"Yale","tag_set":"cliff_organizations","tag_sets_id":2388,"tags_id":9362286},{"stories_id":538278012,"tag":"ABC","tag_set":"cliff_organizations","tag_sets_id":2388,"tags_id":9362473},{"stories_id":538278012,"tag":"Supreme Court","tag_set":"cliff_organizations","tag_sets_id":2388,"tags_id":9362719},{"stories_id":538278012,"tag":"Senate","tag_set":"cliff_organizations","tag_sets_id":2388,"tags_id":9362741},{"stories_id":538278012,"tag":"Hillary Clinton","tag_set":"cliff_people","tag_sets_id":2389,"tags_id":9362747},{"stories_id":538278012,"tag":"Barack Obama","tag_set":"cliff_people","tag_sets_id":2389,"tags_id":9362763},{"stories_id":538278012,"tag":"Marco Rubio","tag_set":"cliff_people","tag_sets_id":2389,"tags_id":9362942},{"stories_id":538278012,"tag":"John McCain","tag_set":"cliff_people","tag_sets_id":2389,"tags_id":9362949},{"stories_id":538278012,"tag":"Congress","tag_set":"cliff_organizations","tag_sets_id":2388,"tags_id":9362962},{"stories_id":538278012,"tag":"House","tag_set":"cliff_organizations","tag_sets_id":2388,"tags_id":9363164},{"stories_id":538278012,"tag":"Mother Jones","tag_set":"cliff_people","tag_sets_id":2389,"tags_id":9363376},{"stories_id":538278012,"tag":"ABC News","tag_set":"cliff_organizations","tag_sets_id":2388,"tags_id":9363445},{"stories_id":538278012,"tag":"State","tag_set":"cliff_organizations","tag_sets_id":2388,"tags_id":9363944},{"stories_id":538278012,"tag":"Environmental Protection Agency","tag_set":"cliff_organizations","tag_sets_id":2388,"tags_id":9363956},{"stories_id":538278012,"tag":"Richard Burr","tag_set":"cliff_people","tag_sets_id":2389,"tags_id":9364116},{"stories_id":538278012,"tag":"EPA","tag_set":"cliff_organizations","tag_sets_id":2388,"tags_id":9364166},{"stories_id":538278012,"tag":"Sierra Club","tag_set":"cliff_organizations","tag_sets_id":2388,"tags_id":9364168},{"stories_id":538278012,"tag":"Boston Globe","tag_set":"cliff_organizations","tag_sets_id":2388,"tags_id":9365544},{"stories_id":538278012,"tag":"John Kasich","tag_set":"cliff_people","tag_sets_id":2389,"tags_id":9366307},{"stories_id":538278012,"tag":"Greg Gianforte","tag_set":"cliff_people","tag_sets_id":2389,"tags_id":9366363},{"stories_id":538278012,"tag":"Wall Street Journal","tag_set":"cliff_organizations","tag_sets_id":2388,"tags_id":9366539},{"stories_id":538278012,"tag":"United States Senate","tag_set":"cliff_organizations","tag_sets_id":2388,"tags_id":9366805},{"stories_id":538278012,"tag":"Mark Kirk","tag_set":"cliff_people","tag_sets_id":2389,"tags_id":9367860},{"stories_id":538278012,"tag":"Tammy Duckworth","tag_set":"cliff_people","tag_sets_id":2389,"tags_id":9367861},{"stories_id":538278012,"tag":"Senate Appropriations Committee","tag_set":"cliff_organizations","tag_sets_id":2388,"tags_id":9368314},{"stories_id":538278012,"tag":"Lisa Murkowski","tag_set":"cliff_people","tag_sets_id":2389,"tags_id":9368354},{"stories_id":538278012,"tag":"University of Colorado","tag_set":"cliff_organizations","tag_sets_id":2388,"tags_id":9368512},{"stories_id":538278012,"tag":"Tesla","tag_set":"cliff_people","tag_sets_id":2389,"tags_id":9369660},{"stories_id":538278012,"tag":"Kate Brown","tag_set":"cliff_people","tag_sets_id":2389,"tags_id":9372440},{"stories_id":538278012,"tag":"Catherine Cortez Masto","tag_set":"cliff_people","tag_sets_id":2389,"tags_id":9372681},{"stories_id":538278012,"tag":"Patrick Murphy","tag_set":"cliff_people","tag_sets_id":2389,"tags_id":9374806},{"stories_id":538278012,"tag":"Rob Portman","tag_set":"cliff_people","tag_sets_id":2389,"tags_id":9374812},{"stories_id":538278012,"tag":"Transportation","tag_set":"cliff_organizations","tag_sets_id":2388,"tags_id":9375351},{"stories_id":538278012,"tag":"Pat McCrory","tag_set":"cliff_people","tag_sets_id":2389,"tags_id":9375354},{"stories_id":538278012,"tag":"Roy Cooper","tag_set":"cliff_people","tag_sets_id":2389,"tags_id":9375355},{"stories_id":538278012,"tag":"Sheldon Adelson","tag_set":"cliff_people","tag_sets_id":2389,"tags_id":9376842},{"stories_id":538278012,"tag":"Chuck Grassley","tag_set":"cliff_people","tag_sets_id":2389,"tags_id":9377138},{"stories_id":538278012,"tag":"Pat Toomey","tag_set":"cliff_people","tag_sets_id":2389,"tags_id":9378330},{"stories_id":538278012,"tag":"Koch brothers","tag_set":"cliff_organizations","tag_sets_id":2388,"tags_id":9378471},{"stories_id":538278012,"tag":"Ron Johnson","tag_set":"cliff_people","tag_sets_id":2389,"tags_id":9381712},{"stories_id":538278012,"tag":"AFL-CIO","tag_set":"cliff_organizations","tag_sets_id":2388,"tags_id":9383509},{"stories_id":538278012,"tag":"Todd Young","tag_set":"cliff_people","tag_sets_id":2389,"tags_id":9384518},{"stories_id":538278012,"tag":"University of New Hampshire","tag_set":"cliff_organizations","tag_sets_id":2388,"tags_id":9384612},{"stories_id":538278012,"tag":"Jason Kander","tag_set":"cliff_people","tag_sets_id":2389,"tags_id":9386726},{"stories_id":538278012,"tag":"Atlanta Journal Constitution","tag_set":"cliff_organizations","tag_sets_id":2388,"tags_id":9396115},{"stories_id":538278012,"tag":"Evan Bayh","tag_set":"cliff_people","tag_sets_id":2389,"tags_id":9397720},{"stories_id":538278012,"tag":"Maggie Hassan","tag_set":"cliff_people","tag_sets_id":2389,"tags_id":9398780},{"stories_id":538278012,"tag":"Colin Van Ostern","tag_set":"cliff_people","tag_sets_id":2389,"tags_id":9398783},{"stories_id":538278012,"tag":"Colorado State University","tag_set":"cliff_organizations","tag_sets_id":2388,"tags_id":9400839},{"stories_id":538278012,"tag":"Jim Justice","tag_set":"cliff_people","tag_sets_id":2389,"tags_id":9408876},{"stories_id":538278012,"tag":"Chris Sununu","tag_set":"cliff_people","tag_sets_id":2389,"tags_id":9408884},{"stories_id":538278012,"tag":"Roy Blunt","tag_set":"cliff_people","tag_sets_id":2389,"tags_id":9412842},{"stories_id":538278012,"tag":"Johnny Isakson","tag_set":"cliff_people","tag_sets_id":2389,"tags_id":9412845},{"stories_id":538278012,"tag":"Steve Bullock","tag_set":"cliff_people","tag_sets_id":2389,"tags_id":9414825},{"stories_id":538278012,"tag":"Senate Energy and Natural Resources Committee","tag_set":"cliff_organizations","tag_sets_id":2388,"tags_id":9416098},{"stories_id":538278012,"tag":"Eric Greitens","tag_set":"cliff_people","tag_sets_id":2389,"tags_id":9420771},{"stories_id":538278012,"tag":"Kelly Ayotte","tag_set":"cliff_people","tag_sets_id":2389,"tags_id":9421967},{"stories_id":538278012,"tag":"Eric Holcomb","tag_set":"cliff_people","tag_sets_id":2389,"tags_id":9422965},{"stories_id":538278012,"tag":"University of Nebraska-Lincoln","tag_set":"cliff_organizations","tag_sets_id":2388,"tags_id":9427882},{"stories_id":538278012,"tag":"Milwaukee Journal Sentinel","tag_set":"cliff_organizations","tag_sets_id":2388,"tags_id":9433963},{"stories_id":538278012,"tag":"Russ Feingold","tag_set":"cliff_people","tag_sets_id":2389,"tags_id":9453817},{"stories_id":538278012,"tag":"Joe Miller","tag_set":"cliff_people","tag_sets_id":2389,"tags_id":9454421},{"stories_id":538278012,"tag":"Phil Scott","tag_set":"cliff_people","tag_sets_id":2389,"tags_id":9455100},{"stories_id":538278012,"tag":"Joe Heck","tag_set":"cliff_people","tag_sets_id":2389,"tags_id":9456547},{"stories_id":538278012,"tag":"Ted Strickland","tag_set":"cliff_people","tag_sets_id":2389,"tags_id":9457885},{"stories_id":538278012,"tag":"Katie McGinty","tag_set":"cliff_people","tag_sets_id":2389,"tags_id":9457888},{"stories_id":538278012,"tag":"Deborah Ross","tag_set":"cliff_people","tag_sets_id":2389,"tags_id":9457889},{"stories_id":538278012,"tag":"Boxer","tag_set":"cliff_people","tag_sets_id":2389,"tags_id":9458853},{"stories_id":538278012,"tag":"Ann Kirkpatrick","tag_set":"cliff_people","tag_sets_id":2389,"tags_id":9474456},{"stories_id":538278012,"tag":"Chris Koster","tag_set":"cliff_people","tag_sets_id":2389,"tags_id":9481358},{"stories_id":538278012,"tag":"Milwaukee Public Radio","tag_set":"cliff_organizations","tag_sets_id":2388,"tags_id":9506637},{"stories_id":538278012,"tag":"Cincinnati Enquirer","tag_set":"cliff_organizations","tag_sets_id":2388,"tags_id":9531110},{"stories_id":538278012,"tag":"Bill Cole","tag_set":"cliff_people","tag_sets_id":2389,"tags_id":9533476},{"stories_id":538278012,"tag":"John Gregg","tag_set":"cliff_people","tag_sets_id":2389,"tags_id":9534102},{"stories_id":538278012,"tag":"Liberty Union Party","tag_set":"cliff_organizations","tag_sets_id":2388,"tags_id":9537612},{"stories_id":538278012,"tag":"Ray Metcalfe","tag_set":"cliff_people","tag_sets_id":2389,"tags_id":9552574},{"stories_id":538278012,"tag":"Sue Minter","tag_set":"cliff_people","tag_sets_id":2389,"tags_id":9562168},{"stories_id":538278012,"tag":"Bud Pierce","tag_set":"cliff_people","tag_sets_id":2389,"tags_id":9562202},{"stories_id":538278012,"tag":"Bill Lee","tag_set":"cliff_people","tag_sets_id":2389,"tags_id":9573162},{"stories_id":538278012,"tag":"Jim Barksdale","tag_set":"cliff_people","tag_sets_id":2389,"tags_id":9580143},{"stories_id":538278012,"tag":"Allen Buckley","tag_set":"cliff_people","tag_sets_id":2389,"tags_id":9580144},{"stories_id":538278012,"tag":"Iowa Public Radio","tag_set":"cliff_organizations","tag_sets_id":2388,"tags_id":9642610},{"stories_id":538278012,"tag":"Environmental Protection","tag_set":"cliff_organizations","tag_sets_id":2388,"tags_id":9691277},{"stories_id":538278012,"tag":"cliff_clavin_v2.4.1","tag_set":"geocoder_version","tag_sets_id":1937,"tags_id":9696677},{"stories_id":538278012,"tag":"Jesse Hunt","tag_set":"cliff_people","tag_sets_id":2389,"tags_id":9802650},{"stories_id":538278012,"tag":"Patty Judge","tag_set":"cliff_people","tag_sets_id":2389,"tags_id":10143526},{"stories_id":538278012,"tag":"NV Energy","tag_set":"cliff_organizations","tag_sets_id":2388,"tags_id":10375272},{"stories_id":538278012,"tag":"Monroe County Health Department","tag_set":"cliff_organizations","tag_sets_id":2388,"tags_id":11438076},{"stories_id":538278012,"tag":"New Hampshire Executive Council","tag_set":"cliff_organizations","tag_sets_id":2388,"tags_id":11480502},{"stories_id":538278012,"tag":"Gulf of Maine Research Institute","tag_set":"cliff_organizations","tag_sets_id":2388,"tags_id":28137052},{"stories_id":538278012,"tag":"Metcalfe Facebook post","tag_set":"cliff_organizations","tag_sets_id":2388,"tags_id":36187781},{"stories_id":538278012,"tag":"Iowa Agribusiness Radio Network","tag_set":"cliff_organizations","tag_sets_id":2388,"tags_id":36187782},{"stories_id":538278012,"tag":"Toomey Senate","tag_set":"cliff_organizations","tag_sets_id":2388,"tags_id":36187783},{"stories_id":538278012,"tag":"[Richard] Alley","tag_set":"cliff_people","tag_sets_id":2389,"tags_id":36187785},{"stories_id":538278012,"tag":"readability-lxml-0.7","tag_set":"extractor_version","tag_sets_id":1354,"tags_id":81092444}],"title":"Climate Change and Policy: Statewide Races to Watch","url":"http://www.newsweek.com/climate-change-and-policy-statewide-races-watch-517971","word_count":null}]