[{"ap_syndicated":null,"collect_date":"2021-02-23 08:50:52.139286","feeds":null,"guid":"https://www.washingtonpost.com/local/md-politics/montgomery-solar-vote/2021/02/22/1d309dc8-7535-11eb-948d-19472e683521_story.html?utm_source=rss&utm_medium=referral&utm_campaign=wp_homepage","language":"en","media_id":2,"media_name":null,"media_url":null,"processed_stories_id":null,"publish_date":"2021-02-23 08:13:33.901639","stories_id":1860645924,"story_tags":[{"stories_id":1860645924,"tag":"geonames_6252001","tag_set":"mc-geocoder@media.mit.edu","tag_sets_id":1011,"tags_id":8878461},{"stories_id":1860645924,"tag":"geonames_4361885","tag_set":"mc-geocoder@media.mit.edu","tag_sets_id":1011,"tags_id":8878524},{"stories_id":1860645924,"tag":"geonames_4076784","tag_set":"mc-geocoder@media.mit.edu","tag_sets_id":1011,"tags_id":8878959},{"stories_id":1860645924,"tag":"nyt_labeller_v1.0.0","tag_set":"nyt_labels_version","tag_sets_id":1964,"tags_id":9360669},{"stories_id":1860645924,"tag":"law and legislation","tag_set":"nyt_labels","tag_sets_id":1963,"tags_id":9360837},{"stories_id":1860645924,"tag":"environment","tag_set":"nyt_labels","tag_sets_id":1963,"tags_id":9360887},{"stories_id":1860645924,"tag":"agriculture","tag_set":"nyt_labels","tag_sets_id":1963,"tags_id":9361156},{"stories_id":1860645924,"tag":"land use policies","tag_set":"nyt_labels","tag_sets_id":1963,"tags_id":9361316},{"stories_id":1860645924,"tag":"county council","tag_set":"cliff_organizations","tag_sets_id":2388,"tags_id":9385705},{"stories_id":1860645924,"tag":"Caroline Taylor","tag_set":"cliff_people","tag_sets_id":2389,"tags_id":9389904},{"stories_id":1860645924,"tag":"Chesapeake Climate Action Network","tag_set":"cliff_organizations","tag_sets_id":2388,"tags_id":9499518},{"stories_id":1860645924,"tag":"Mike Tidwell","tag_set":"cliff_people","tag_sets_id":2389,"tags_id":9499528},{"stories_id":1860645924,"tag":"Craig Rice","tag_set":"cliff_people","tag_sets_id":2389,"tags_id":10132205},{"stories_id":1860645924,"tag":"Hans Riemer","tag_set":"cliff_people","tag_sets_id":2389,"tags_id":10657530},{"stories_id":1860645924,"tag":"Sidney Katz","tag_set":"cliff_people","tag_sets_id":2389,"tags_id":11033568},{"stories_id":1860645924,"tag":"Kumar P. Barve","tag_set":"cliff_people","tag_sets_id":2389,"tags_id":20207786},{"stories_id":1860645924,"tag":"Andrew Friedson","tag_set":"cliff_people","tag_sets_id":2389,"tags_id":27932085},{"stories_id":1860645924,"tag":"Montgomery County Sierra Club","tag_set":"cliff_organizations","tag_sets_id":2388,"tags_id":47040464},{"stories_id":1860645924,"tag":"House of Delegates Environment and Transportation Committee","tag_set":"cliff_organizations","tag_sets_id":2388,"tags_id":52726454},{"stories_id":1860645924,"tag":"Montgomery Countryside Alliance","tag_set":"cliff_organizations","tag_sets_id":2388,"tags_id":74924639},{"stories_id":1860645924,"tag":"readability-lxml-0.8.1","tag_set":"extractor_version","tag_sets_id":1354,"tags_id":228516910},{"stories_id":1860645924,"tag":"cliff_clavin_v2.6.1","tag_set":"geocoder_version","tag_sets_id":1937,"tags_id":228516911}],"title":"Montgomery County to decide whether to allow solar in agricultural reserve","url":"https://www.washingtonpost.com/local/md-politics/montgomery-solar-vote/2021/02/22/1d309dc8-7535-11eb-948d-19472e683521_story.html?utm_source=rss&utm_medium=referral&utm_campaign=wp_homepage","word_count":null}]